asteroids/__init__.py
asteroids/__main__.py
asteroids/asteroid.py
asteroids/asteroidfield.py
asteroids/circleshape.py
asteroids/constants.py
asteroids/main.py
asteroids/player.py
asteroids/shot.py
nghiango_asteroids-1.0.dist-info/METADATA
nghiango_asteroids-1.0.dist-info/WHEEL
nghiango_asteroids-1.0.dist-info/entry_points.txt
nghiango_asteroids-1.0.dist-info/top_level.txt
nghiango_asteroids-1.0.dist-info/RECORD
