Metadata-Version: 2.1
Name: nghiango-asteroids
Version: 1.0
Requires-Dist: pygame
